censorpy/__init__.py
censorpy/censorpy.py
censorpy/handlers/__init__.py
censorpy/handlers/censorHandler.py
censorpy/handlers/checkerHandler.py
censorpy-0.2.1.dist-info/METADATA
censorpy-0.2.1.dist-info/WHEEL
censorpy-0.2.1.dist-info/top_level.txt
censorpy-0.2.1.dist-info/RECORD
