Metadata-Version: 2.1
Name: censorpy
Version: 0.2.1
Summary: Censor words and phrases with censorpy.
Author: NotKatsu
Author-email: katsudiscord@outlook.com
Keywords: python,censor,censorpy,words,censoring,block
Classifier: Development Status :: 1 - Planning
Classifier: Intended Audience :: Developers
Classifier: Programming Language :: Python :: 3
Classifier: Operating System :: Unix
Classifier: Operating System :: MacOS :: MacOS X
Classifier: Operating System :: Microsoft :: Windows
Requires-Dist: unidecode
